doc/source/conf.py
examples/plot_moments.py
examples/plot_power_spectra.py
highiq/__init__.py
highiq/calc/__init__.py
highiq/calc/moments.py
highiq/calc/spectra.py
highiq/io/__init__.py
highiq/io/arm_data.py
highiq/testing/__init__.py
highiq-2025.11.10.dist-info/licenses/LICENSE
tests/test_highiq.py
highiq-2025.11.10.dist-info/METADATA
highiq-2025.11.10.dist-info/WHEEL
highiq-2025.11.10.dist-info/top_level.txt
highiq-2025.11.10.dist-info/RECORD
