Metadata-Version: 2.4
Name: highiq
Version: 2025.11.10
Summary: Package for processing Doppler lidar spectra
Requires-Python: >=3.9
License-File: LICENSE
Requires-Dist: numpy
Requires-Dist: scipy
Requires-Dist: xarray
Requires-Dist: pint
Requires-Dist: netcdf4
Dynamic: license-file
